cdn_definitions/__init__.py
cdn_definitions/data.json
cdn_definitions/data.yaml
cdn_definitions/schema.json
cdn_definitions/schema.yaml
cdn_definitions/_impl/__init__.py
cdn_definitions-3.4.1.dist-info/LICENSE
cdn_definitions-3.4.1.dist-info/METADATA
cdn_definitions-3.4.1.dist-info/WHEEL
cdn_definitions-3.4.1.dist-info/top_level.txt
cdn_definitions-3.4.1.dist-info/RECORD
