Metadata-Version: 2.1
Name: cdn-definitions
Version: 3.4.1
Summary: Data definitions for Red Hat's content delivery network
Home-page: https://github.com/release-engineering/cdn-definitions
Author: Rohan McGovern
Author-email: rmcgover@redhat.com
License: GNU General Public License
Project-URL: Documentation, https://release-engineering.github.io/cdn-definitions/
Project-URL: Changelog, https://github.com/release-engineering/cdn-definitions/blob/master/CHANGELOG.md
Platform: UNKNOWN
Classifier: Development Status :: 4 - Beta
Classifier: Intended Audience :: Developers
Classifier: License :: OSI Approved :: GNU General Public License v3 or later (GPLv3+)
Classifier: Programming Language :: Python :: 3
Classifier: Topic :: Software Development :: Libraries :: Python Modules
Requires-Dist: frozendict
Requires-Dist: frozenlist2
Requires-Dist: PyYAML
Requires-Dist: requests
